sapiens_model/__init__.py
sapiens_model/sapiens_model.py
sapiens_model-2.0.3.dist-info/LICENSE.txt
sapiens_model-2.0.3.dist-info/METADATA
sapiens_model-2.0.3.dist-info/WHEEL
sapiens_model-2.0.3.dist-info/top_level.txt
sapiens_model-2.0.3.dist-info/RECORD
