Metadata-Version: 2.2
Name: sapiens_model
Version: 2.0.3
Home-page: https://github.com/sapiens-technology/sapiens_architecture_with_sapiens_model
Author: SAPIENS TECHNOLOGY
License: Proprietary Software
License-File: LICENSE.txt
Requires-Dist: semantic-comparison-network
Requires-Dist: scnetwork
Requires-Dist: scn
Requires-Dist: hur
Requires-Dist: hur-multimodal
Requires-Dist: sapiens-cpu
Requires-Dist: mgt
Requires-Dist: sapiens-dataset
Requires-Dist: utilities-nlp
Requires-Dist: tqdm
Requires-Dist: certifi
Requires-Dist: INFINITE-CONTEXT-WINDOW
Dynamic: author
Dynamic: home-page
Dynamic: license
Dynamic: requires-dist
